firefighter/__init__.py
firefighter/logging.py
firefighter-0.1.0.dist-info/METADATA
firefighter-0.1.0.dist-info/RECORD
firefighter-0.1.0.dist-info/WHEEL
firefighter-0.1.0.dist-info/top_level.txt
