Metadata-Version: 2.1
Name: firefighter
Version: 0.1.0
Summary: AWS Kinesis Data Firehose logging handler
Home-page: UNKNOWN
License: Apache Software License
Keywords: firehose,aws,kinesis
Platform: UNKNOWN
Classifier: Development Status :: 3 - Alpha
Classifier: Intended Audience :: Developers
Classifier: License :: OSI Approved :: Apache Software License
Classifier: Programming Language :: Python :: 2.6
Classifier: Programming Language :: Python :: 2.7
Classifier: Programming Language :: Python :: 3.4
Classifier: Programming Language :: Python :: 3.5
Classifier: Programming Language :: Python :: 3.6
Classifier: Programming Language :: Python :: 3.7
Classifier: Topic :: System :: Logging
Provides-Extra: tests
Provides-Extra: docs
Requires-Dist: boto3 (>=1.7.81)
Provides-Extra: docs
Requires-Dist: Sphinx (>=1.7.6); extra == 'docs'
Provides-Extra: tests
Requires-Dist: flake8; extra == 'tests'
Requires-Dist: flake8-import-order (<0.19,>=0.18); extra == 'tests'
Requires-Dist: flake8-import-order-spoqa (<1.5,>=1.4.1); extra == 'tests'
Requires-Dist: moto (<1.4,>=1.3.4); extra == 'tests'
Requires-Dist: pytest (>=3.7.1); extra == 'tests'
Requires-Dist: pytest-flake8 (<1.1,>=1.0.2); extra == 'tests'
Requires-Dist: tox (>=3.2.1); extra == 'tests'
